epsproc/AFBLM.py
epsproc/IO.py
epsproc/MFBLM.py
epsproc/MFPAD.py
epsproc/__init__.py
epsproc/_sns_matrixMod.py
epsproc/basicPlotters.py
epsproc/sphCalc.py
epsproc/sphPlot.py
epsproc/util.py
epsproc/calc/__init__.py
epsproc/calc/density.py
epsproc/calc/density_v1.py
epsproc/calc/density_v2.py
epsproc/classes/_IO.py
epsproc/classes/__init__.py
epsproc/classes/_plotters.py
epsproc/classes/_selectors.py
epsproc/classes/base.py
epsproc/classes/base_bk151020.py
epsproc/classes/multiJob.py
epsproc/classes/multiJob_v1_131020.py
epsproc/efield/__init__.py
epsproc/efield/efields.py
epsproc/geomFunc/__init__.py
epsproc/geomFunc/afblmGeom.py
epsproc/geomFunc/afblmGeom_bk161020.py
epsproc/geomFunc/afblmGeom_v1-ref_2020.py
epsproc/geomFunc/geomCalc.py
epsproc/geomFunc/geomUtils.py
epsproc/geomFunc/lfblmGeom.py
epsproc/geomFunc/mfblmGeom.py
epsproc/geomFunc/mfblmGeom_Dev.py
epsproc/geomFunc/phaseCons-verified_130420.py
epsproc/geomFunc/phaseCons-verified_CG_230620.py
epsproc/geomFunc/w3jVecMethods.py
epsproc/geomFunc/wNjSympyWrapper.py
epsproc/plot/__init__.py
epsproc/plot/hvPlotters.py
epsproc/plot/util.py
epsproc/util/__init__.py
epsproc/util/conversion.py
epsproc/util/env.py
epsproc/util/epsdata.py
epsproc/util/listFuncs.py
epsproc/util/misc.py
epsproc/util/selectors.py
epsproc/util/summary.py
epsproc/vol/__init__.py
epsproc/vol/orbPlot.py
epsproc/vol/setOptions.py
epsproc/vol/set_plot_options_json.py
epsproc/vol/wfPlot.py
tests/__init__.py
ePSproc-1.3.1.dist-info/LICENSE
ePSproc-1.3.1.dist-info/METADATA
ePSproc-1.3.1.dist-info/WHEEL
ePSproc-1.3.1.dist-info/top_level.txt
ePSproc-1.3.1.dist-info/RECORD
