Metadata-Version: 2.1
Name: ePSproc
Version: 1.3.1
Summary: Post-processing suite for ePolyScat calculations (Matlab & Python).
Home-page: https://github.com/phockett/ePSproc
Author: Paul Hockett
Author-email: epsproc@gmail.com
Maintainer: Paul Hockett
Maintainer-email: epsproc@gmail.com
License: GNU3
Platform: UNKNOWN
Classifier: Development Status :: 4 - Beta
Classifier: Intended Audience :: Developers
Classifier: Intended Audience :: Science/Research
Classifier: License :: OSI Approved :: GNU General Public License v3 or later (GPLv3+)
Classifier: Natural Language :: English
Classifier: Operating System :: OS Independent
Classifier: Programming Language :: Python :: 3.5
Classifier: Programming Language :: Python :: 3.6
Classifier: Programming Language :: Python :: Implementation :: CPython
Classifier: Programming Language :: Python :: Implementation :: PyPy
Classifier: Topic :: Scientific/Engineering :: Physics
Classifier: Topic :: Scientific/Engineering :: Chemistry
Requires-Dist: numpy-quaternion
Requires-Dist: numpy
Requires-Dist: scipy
Requires-Dist: xarray
Requires-Dist: pandas
Requires-Dist: matplotlib
Requires-Dist: seaborn (==0.9.0)
Requires-Dist: spherical-functions
Requires-Dist: numba
Requires-Dist: pyvista
Requires-Dist: cclib
Requires-Dist: holoviews
Requires-Dist: plotly
Requires-Dist: jupyter-dash
